{
    "name": "News",
    "sections": [
        {
            "name": "Header",
            "id": "headerSection",
            "fields": [
                {
                    "name": "Subtitle",
                    "type": "textarea",
                    "id": "headerSubtitle",
                    "value": "See what's going on with our company!"
                },
                {
                    "name": "Category",
                    "type": "select",
                    "id": "category",
                    "options": [
                        {
                            "name": "All",
                            "value": "all"
                        },
                        {
                            "name": "Company",
                            "value": "company"
                        },
                        {
                            "name": "Product",
                            "value": "product"
                        }
                    ]
                }
            ]
        }
    ]
}